pyhud/__init__.py
hud_client-0.0.0a0.dist-info/METADATA
hud_client-0.0.0a0.dist-info/WHEEL
hud_client-0.0.0a0.dist-info/top_level.txt
hud_client-0.0.0a0.dist-info/RECORD
